pysrcds-0.1.5.dist-info/DESCRIPTION.rst
pysrcds-0.1.5.dist-info/METADATA
pysrcds-0.1.5.dist-info/RECORD
pysrcds-0.1.5.dist-info/WHEEL
pysrcds-0.1.5.dist-info/metadata.json
pysrcds-0.1.5.dist-info/top_level.txt
srcds/__init__.py
srcds/logparser.py
srcds/objects.py
srcds/rcon.py
srcds/events/__init__.py
srcds/events/csgo.py
srcds/events/generic.py
